ceramic/IdData.py
ceramic/Mosaic.py
ceramic/Tile.py
ceramic/TrainingTestXy.py
ceramic/TransformedModel.py
ceramic/ValidationXy.py
ceramic/Xy.py
ceramic/XyRegression.py
ceramic/__init__.py
ceramic/get_cross_validation_by_group.py
ceramic/validate_fold.py
ceramic-2020.11.12.dist-info/METADATA
ceramic-2020.11.12.dist-info/WHEEL
ceramic-2020.11.12.dist-info/top_level.txt
ceramic-2020.11.12.dist-info/RECORD
