Metadata-Version: 2.1
Name: ceramic
Version: 2020.11.12
Summary: Python library for defining data tables as tiles
Home-page: https://github.com/idin/ceramic
Author: Idin
Author-email: py@idin.ca
License: MIT
Platform: UNKNOWN
Classifier: Development Status :: 3 - Alpha
Classifier: Intended Audience :: Developers
Classifier: Programming Language :: Python :: 3 :: Only
Classifier: Programming Language :: Python :: 3.6
Classifier: Programming Language :: Python :: 3.7
Classifier: Topic :: Software Development :: Libraries :: Python Modules
Requires-Python: ~=3.6
Requires-Dist: sklearn
Requires-Dist: pandas
Requires-Dist: joblib
Requires-Dist: ravenclaw
Requires-Dist: chronometry
Requires-Dist: nightingale
Requires-Dist: pensieve
Requires-Dist: slytherin
